frettipy.py
frettipy-0.7.dist-info/entry_points.txt
frettipy-0.7.dist-info/licenses/LICENSE
frettipy-0.7.dist-info/WHEEL
frettipy-0.7.dist-info/METADATA
frettipy-0.7.dist-info/RECORD
