Metadata-Version: 2.4
Name: frettipy
Version: 0.7
Summary: No fretting about pretty Python
Author: Jan Berges
Requires-Python: >=2.7
Classifier: License :: OSI Approved :: Zero-Clause BSD (0BSD)
Classifier: Programming Language :: Python
License-File: LICENSE
Project-URL: Homepage, https://github.com/janberges/frettipy
